[
  {
    "file_name": "AC_ATTWN_CD1.iso",
    "mime_type": "application/x-cd-image",
    "file_id": "BQACAgQAAx0CS2Z5_gACA5Zgeqa8p9pOHLKYwlH3JuDNTLiAFQACdggAAgStaFJR1n5_cFL5ah8E",
    "file_unique_id": "AgADdggAAgStaFI",
    "file_size": 690810880
  },
  {
    "file_name": "AC_ATTWN_CD2.iso",
    "mime_type": "application/x-cd-image",
    "file_id": "BQACAgQAAx0CS2Z5_gACA5dgeqa8sTz_hYB4Bf5jxUsb-iF1NAACdwgAAgStaFJ5hm8TlaPlVB8E",
    "file_unique_id": "AgADdwgAAgStaFI",
    "file_size": 679725056
  },
  {
    "file_name": "And Then There Were None Serial.txt",
    "mime_type": "text/plain",
    "file_id": "BQACAgQAAx0CS2Z5_gACA5hgeqa8k4e6u7WjZWTTE7_jb4sO_wACRggAAmhqYVI-9y0Dm1Hw0x8E",
    "file_unique_id": "AgADRggAAmhqYVI",
    "file_size": 12
  },
  {
    "file_name": "Agatha Christie And Then There Were None Manual.pdf",
    "mime_type": "application/pdf",
    "file_id": "BQACAgQAAx0ES2Z5_gACCydhAYBmXiLrOEFEqJuA491WG-nBNQACrwoAAs-ACFPULWgwj0OR9iAE",
    "file_unique_id": "AgADrwoAAs-ACFM",
    "file_size": 19890930
  }
]