{
  "title": [
    "Pocket Fighter"
  ],
  "titlefa": [
    "پاکت فایتر"
  ],
  "producer": [
    "asrebazi"
  ],
  "publisher": [
    "asrebazi"
  ],
  "price": [
    40000
  ],
  "release_date": [],
  "released_on": [
    "CD"
  ],
  "no_of_discs": [
    1
  ],
  "defects": [],
  "games": [
    {
      "title": [],
      "titlefa": [],
      "dubbed": false,
      "modified": false,
      "subtitle": false,
      "iranian": true
    }
  ],
  "selling": false,
  "platform": [
    "Windows"
  ],
  "manuals": false,
  "contributors": [
    {
      "username": "ruinerart",
      "contribute": [
        "game",
        "cover"
      ]
    },
    {
      "username": "Aammiirr5732",
      "contribute": [
        "game",
        "cover"
      ]
    },
    {
      "username": "alihardan",
      "contribute": [
        "details"
      ]
    }
  ],
  "links": []
}