{
  "title": [
    "Ice Age: Dawn of the Dinosaurs",
    "Ice Age 3: Dawn of the Dinosaurs"
  ],
  "titlefa": [
    "عصر یخبندان ۳: طلوع دایناسورها"
  ],
  "producer": [
    "asrebazi",
    "modern"
  ],
  "publisher": [
    "asrebazi",
    "modern"
  ],
  "price": [],
  "release_date": [
    {
      "date": "2009-08-18",
      "ref": "بر اساس تاریخ فایل‌های دیسک."
    }
  ],
  "released_on": [
    "DVD"
  ],
  "no_of_discs": [
    1
  ],
  "defects": [],
  "games": [
    {
      "title": [],
      "titlefa": [],
      "dubbed": true,
      "modified": false,
      "subtitle": false,
      "iranian": false
    }
  ],
  "selling": false,
  "platform": [
    "Windows"
  ],
  "manuals": false,
  "contributors": [
    {
      "username": "AG_e_e_kA",
      "contribute": [
        "game"
      ]
    },
    {
      "username": "pouryajfr",
      "contribute": [
        "game"
      ]
    },
    {
      "username": "alihardan",
      "contribute": [
        "game",
        "cover"
      ]
    }
  ],
  "links": [],
  "ia_id": "ice-age-dawn-of-the-dinosaurs-asrebazi-modern"
}