[
  {
    "file_name": "PES2016-Lige-94-95-Modern.part1.rar",
    "mime_type": "application/x-rar-compressed",
    "file_id": "BQACAgQAAx0ES2Z5_gACD11hJavyqznTOL4x5J7g3S1terU51QACTwsAAk-S-FCv2jntVoudByAE",
    "file_unique_id": "AgADTwsAAk-S-FA",
    "file_size": 2097152000
  },
  {
    "file_name": "PES2016-Lige-94-95-Modern.part2.rar",
    "mime_type": "application/x-rar-compressed",
    "file_id": "BQACAgQAAx0ES2Z5_gACD15hJav14E143AOku8Bp_eIgPVe6AANQCwACT5L4UDTfN2RjPVGEIAQ",
    "file_unique_id": "AgADUAsAAk-S-FA",
    "file_size": 2097152000
  },
  {
    "file_name": "PES2016-Lige-94-95-Modern.part3.rar",
    "mime_type": "application/x-rar-compressed",
    "file_id": "BQACAgQAAx0ES2Z5_gACD19hJav4rjwzcO6u616nI8n15NahGwACUQsAAk-S-FA7ELQD13ZbICAE",
    "file_unique_id": "AgADUQsAAk-S-FA",
    "file_size": 2053243522
  }
]