[
  {
    "file_name": "qalamroye tariki DISK1.part1.rar",
    "mime_type": "application/rar",
    "file_id": "BQACAgQAAx0CS2Z5_gACEC5hlsMc_nn1Ga3m0KYHqh7SzMQQPgACQA4AAkBkeFG_n35iUAABtv8iBA",
    "file_unique_id": "AgADQA4AAkBkeFE",
    "file_size": 2097152000
  },
  {
    "file_name": "qalamroye tariki DISK1.part2.rar",
    "mime_type": "application/rar",
    "file_id": "BQACAgQAAx0CS2Z5_gACEC1hlsMcFztiPSWcDs8y_sPrP_UP8wACPg4AAkBkeFEhEuNCvCBYICIE",
    "file_unique_id": "AgADPg4AAkBkeFE",
    "file_size": 1037768563
  },
  {
    "file_name": "qalamroye tariki DISK2.iso",
    "mime_type": "application/x-iso9660-image",
    "file_id": "BQACAgQAAx0CS2Z5_gACEC9hlsMpBvfdSpIcmPKRsYcOpdqenQACZQoAAtzncVHMsUap65RkOiIE",
    "file_unique_id": "AgADZQoAAtzncVE",
    "file_size": 645642240
  }
]