[
  {
    "file_id": "BQACAgQAAx0ES2Z5_gACEr5iEJtInZCZatz7M2OKyfiA8HF0QQAC9xQAAvfBiFCbX4jyjTBIRh4E",
    "file_unique_id": "AgAD9xQAAvfBiFA",
    "file_name": "the-westerner-magmasoft-photos.zip",
    "mime_type": "application/zip",
    "file_size": 31556463,
    "date": 1645255496,
    "thumbs": null
  },
  {
    "file_name": "Westerner.iso",
    "mime_type": "application/x-iso9660-image",
    "file_id": "BQACAgQAAx0CS2Z5_gACBK1ghe1Ll_sC7iHPC54hmxF8hyP1ZQAC9ggAAvabmFOJ7P9EkmvVpx8E",
    "file_unique_id": "AgAD9ggAAvabmFM",
    "file_size": 533026816
  }
]