{
    "contributors": [
        {
            "contribute": [
                "game",
                "cover",
                "details"
            ],
            "username": "Sepehr_Gamer"
        },
        {
            "contribute": [
                "details"
            ],
            "username": "alihardan"
        }
    ],
    "defects": [],
    "description": "",
    "games": [
        {
            "dubbed": true,
            "iranian": false,
            "modified": false,
            "subtitle": false,
            "title": [],
            "titlefa": []
        }
    ],
    "ia_id": "code-of-honor-the-french-foreign-legion-newtech",
    "links": [],
    "manuals": false,
    "no_of_discs": [
        1
    ],
    "platform": [
        "Windows"
    ],
    "price": [],
    "producer": [
        "newtech"
    ],
    "publisher": [
        "newtech"
    ],
    "release_date": [
        {
            "date": "2008-09-18",
            "ref": "بر اساس تاریخ فایل‌های دیسک."
        }
    ],
    "released_on": [
        "CD"
    ],
    "selling": false,
    "title": [
        "Code of Honor: The French Foreign Legion"
    ],
    "titlefa": [
        "رمز افتخار: هنگ بیگانه فرانسوی"
    ]
}