[
  {
    "file_id": "BQACAgQAAx0ES2Z5_gACESFh9UieZ3ag--knrB5cbqrvkEnTFwACwgkAAlFcsFPQactfw-ajmB4E",
    "file_unique_id": "AgADwgkAAlFcsFM",
    "file_name": "alcatraz-magmasoft-photos.zip",
    "mime_type": "application/zip",
    "file_size": 29184188,
    "date": 1643464862,
    "thumbs": null
  },
  {
    "file_name": "Alcatraz.iso",
    "mime_type": "application/x-iso9660-image",
    "file_id": "BQACAgQAAx0CS2Z5_gACB9BgthpBUVip402CcRpp7YlYGFMMkgACLggAAjUwqFBfufmfqXCrVx8E",
    "file_unique_id": "AgADLggAAjUwqFA",
    "file_size": 216788992
  }
]